{"name":"build-javascript","namedChunkGroups":{"polyfill":{"name":"polyfill","assets":[{"name":"webpack-runtime-200bf1240083f0dc2b6b.js","size":3254},{"name":"polyfill-7f400bf4348caa9fc607.js","size":85840}],"filteredAssets":0,"assetsSize":89094,"filteredAuxiliaryAssets":2,"auxiliaryAssetsSize":221237},"app":{"name":"app","assets":[{"name":"webpack-runtime-200bf1240083f0dc2b6b.js","size":3254},{"name":"framework-83301fedf86e9aa72a6a.js","size":140725},{"name":"styles.af2f970edcf1322a4bcd.css","size":1988},{"name":"app-b4605b8df6eb3d005d6c.js","size":99758}],"filteredAssets":0,"assetsSize":245725,"filteredAuxiliaryAssets":3,"auxiliaryAssetsSize":735595},"component---src-pages-404-tsx":{"name":"component---src-pages-404-tsx","assets":[{"name":"component---src-pages-404-tsx-7b7c0213f324990804c7.js","size":805}],"filteredAssets":0,"assetsSize":805,"filteredAuxiliaryAssets":1,"auxiliaryAssetsSize":2139},"component---src-pages-index-tsx":{"name":"component---src-pages-index-tsx","assets":[{"name":"component---src-pages-index-tsx-206e8d5a54ef743d7e3d.js","size":53529}],"filteredAssets":0,"assetsSize":53529,"filteredAuxiliaryAssets":2,"auxiliaryAssetsSize":606366}},"assetsByChunkName":{"polyfill":["webpack-runtime-200bf1240083f0dc2b6b.js","polyfill-7f400bf4348caa9fc607.js"],"app":["webpack-runtime-200bf1240083f0dc2b6b.js","framework-83301fedf86e9aa72a6a.js","styles.af2f970edcf1322a4bcd.css","app-b4605b8df6eb3d005d6c.js"],"component---src-pages-404-tsx":["component---src-pages-404-tsx-7b7c0213f324990804c7.js"],"component---src-pages-index-tsx":["component---src-pages-index-tsx-206e8d5a54ef743d7e3d.js"]},"childAssetsByChunkName":{}}